{
  "lastUpdated": "2026-04-08T02:17:02.862Z",
  "schedules": [
    {
      "id": "spotvnow-2026-04-08-38025",
      "date": "2026-04-08",
      "time": "04:00",
      "sport": "축구",
      "league": "챔피언스리그",
      "homeTeam": "레알 마드리드",
      "awayTeam": "바이에른 뮌헨",
      "platform": "SPOTV NOW",
      "koreanCommentary": true
    },
    {
      "id": "spotvnow-2026-04-08-38026",
      "date": "2026-04-08",
      "time": "04:00",
      "sport": "축구",
      "league": "챔피언스리그",
      "homeTeam": "스포르팅 CP",
      "awayTeam": "아스날",
      "platform": "SPOTV NOW",
      "koreanCommentary": true
    },
    {
      "id": "spotvnow-2026-04-08-38051",
      "date": "2026-04-08",
      "time": "07:40",
      "sport": "야구",
      "league": "MLB",
      "homeTeam": "샌디에이고 파드리스",
      "awayTeam": "피츠버그 파이리츠",
      "platform": "SPOTV NOW",
      "koreanCommentary": false
    },
    {
      "id": "spotvnow-2026-04-08-38052",
      "date": "2026-04-08",
      "time": "08:05",
      "sport": "야구",
      "league": "MLB",
      "homeTeam": "애슬레틱스",
      "awayTeam": "뉴욕 양키스",
      "platform": "SPOTV NOW",
      "koreanCommentary": true
    },
    {
      "id": "spotvnow-2026-04-08-38053",
      "date": "2026-04-08",
      "time": "08:07",
      "sport": "야구",
      "league": "MLB",
      "homeTeam": "LA 다저스",
      "awayTeam": "토론토 블루제이스",
      "platform": "SPOTV NOW",
      "koreanCommentary": true
    },
    {
      "id": "coupang-2026-04-08-08:30-NBA-마이애미-토론토",
      "date": "2026-04-08",
      "time": "08:30",
      "sport": "농구",
      "league": "NBA",
      "homeTeam": "마이애미",
      "awayTeam": "토론토",
      "platform": "쿠팡플레이",
      "koreanCommentary": true
    },
    {
      "id": "coupang-2026-04-08-09:00-NBA-샬럿-보스턴",
      "date": "2026-04-08",
      "time": "09:00",
      "sport": "농구",
      "league": "NBA",
      "homeTeam": "샬럿",
      "awayTeam": "보스턴",
      "platform": "쿠팡플레이",
      "koreanCommentary": true
    },
    {
      "id": "spotvnow-2026-04-08-38054",
      "date": "2026-04-08",
      "time": "09:40",
      "sport": "야구",
      "league": "MLB",
      "homeTeam": "휴스턴 애스트로스",
      "awayTeam": "콜로라도 로키스",
      "platform": "SPOTV NOW",
      "koreanCommentary": false
    },
    {
      "id": "spotv-2026-04-08-09:50-SPOTV 고교야구 시리즈 <2026",
      "date": "2026-04-08",
      "time": "09:50",
      "sport": "야구",
      "league": "고교야구",
      "homeTeam": "제물포고",
      "awayTeam": "광주제일고",
      "platform": "SPOTV",
      "koreanCommentary": true
    },
    {
      "id": "spotvnow-2026-04-08-38101",
      "date": "2026-04-08",
      "time": "10:00",
      "sport": "야구",
      "league": "고교야구",
      "homeTeam": "제물포고",
      "awayTeam": "광주제일고",
      "platform": "SPOTV NOW",
      "koreanCommentary": true
    },
    {
      "id": "spotvnow-2026-04-08-38055",
      "date": "2026-04-08",
      "time": "10:38",
      "sport": "야구",
      "league": "MLB",
      "homeTeam": "애틀랜타 브레이브스",
      "awayTeam": "LA 에인절스",
      "platform": "SPOTV NOW",
      "koreanCommentary": false
    },
    {
      "id": "spotvnow-2026-04-08-38056",
      "date": "2026-04-08",
      "time": "10:45",
      "sport": "야구",
      "league": "MLB",
      "homeTeam": "필라델피아 필리스",
      "awayTeam": "샌프란시스코 자이언츠",
      "platform": "SPOTV NOW",
      "koreanCommentary": true
    },
    {
      "id": "coupang-2026-04-08-11:00-북중미 챔피언스컵-LAFC-크루스 아술",
      "date": "2026-04-08",
      "time": "11:00",
      "sport": "축구",
      "league": "북중미 챔피언스컵",
      "homeTeam": "LAFC",
      "awayTeam": "크루스 아술",
      "platform": "쿠팡플레이",
      "koreanCommentary": true
    },
    {
      "id": "coupang-2026-04-08-11:00-NBA-새크라멘토-골든스테이트",
      "date": "2026-04-08",
      "time": "11:00",
      "sport": "농구",
      "league": "NBA",
      "homeTeam": "새크라멘토",
      "awayTeam": "골든스테이트",
      "platform": "쿠팡플레이",
      "koreanCommentary": true
    },
    {
      "id": "coupang-2026-04-08-11:30-NBA-오클라호마시티-LA 레이커스",
      "date": "2026-04-08",
      "time": "11:30",
      "sport": "농구",
      "league": "NBA",
      "homeTeam": "오클라호마시티",
      "awayTeam": "LA 레이커스",
      "platform": "쿠팡플레이",
      "koreanCommentary": true
    },
    {
      "id": "coupang-2026-04-08-12:00-NBA-휴스턴-피닉스",
      "date": "2026-04-08",
      "time": "12:00",
      "sport": "농구",
      "league": "NBA",
      "homeTeam": "휴스턴",
      "awayTeam": "피닉스",
      "platform": "쿠팡플레이",
      "koreanCommentary": true
    },
    {
      "id": "spotvnow-2026-04-08-38102",
      "date": "2026-04-08",
      "time": "13:00",
      "sport": "야구",
      "league": "고교야구",
      "homeTeam": "부산고",
      "awayTeam": "덕수고",
      "platform": "SPOTV NOW",
      "koreanCommentary": true
    },
    {
      "id": "tvn-2026-04-08-13:00-2026 메디힐 KBO 퓨처스리그",
      "date": "2026-04-08",
      "time": "13:00",
      "sport": "야구",
      "league": "KBO",
      "homeTeam": "KIA",
      "awayTeam": "삼성",
      "platform": "tvN SPORTS",
      "koreanCommentary": true
    },
    {
      "id": "spotv-2026-04-08-18:15-2026 KBO리그 한화:SSG(문학",
      "date": "2026-04-08",
      "time": "18:15",
      "sport": "야구",
      "league": "KBO",
      "homeTeam": "한화",
      "awayTeam": "SSG",
      "platform": "SPOTV",
      "koreanCommentary": true
    },
    {
      "id": "spotv2-2026-04-08-18:15-2026 KBO리그 키움:두산 (잠실",
      "date": "2026-04-08",
      "time": "18:15",
      "sport": "야구",
      "league": "KBO",
      "homeTeam": "키움",
      "awayTeam": "두산",
      "platform": "SPOTV2",
      "koreanCommentary": true
    },
    {
      "id": "mbc-2026-04-08-18:15-2026 신한 SOL KBO리그",
      "date": "2026-04-08",
      "time": "18:15",
      "sport": "야구",
      "league": "KBO",
      "homeTeam": "KT",
      "awayTeam": "롯데",
      "platform": "MBC SPORTS+",
      "koreanCommentary": true
    },
    {
      "id": "sbs-sports-2026-04-08-18:20-2026 KBO리그 LG:NC",
      "date": "2026-04-08",
      "time": "18:20",
      "sport": "야구",
      "league": "KBO",
      "homeTeam": "LG",
      "awayTeam": "NC",
      "platform": "SBS Sports",
      "koreanCommentary": true
    },
    {
      "id": "tving-2026-04-08-18:30-KBO-KT-롯데",
      "date": "2026-04-08",
      "time": "18:30",
      "sport": "야구",
      "league": "KBO",
      "homeTeam": "롯데",
      "awayTeam": "KT",
      "platform": "티빙",
      "koreanCommentary": true
    },
    {
      "id": "tving-2026-04-08-18:30-KBO-삼성-KIA",
      "date": "2026-04-08",
      "time": "18:30",
      "sport": "야구",
      "league": "KBO",
      "homeTeam": "KIA",
      "awayTeam": "삼성",
      "platform": "티빙",
      "koreanCommentary": true
    },
    {
      "id": "tving-2026-04-08-18:30-KBO-LG-NC",
      "date": "2026-04-08",
      "time": "18:30",
      "sport": "야구",
      "league": "KBO",
      "homeTeam": "NC",
      "awayTeam": "LG",
      "platform": "티빙",
      "koreanCommentary": true
    },
    {
      "id": "tving-2026-04-08-18:30-KBO-키움-두산",
      "date": "2026-04-08",
      "time": "18:30",
      "sport": "야구",
      "league": "KBO",
      "homeTeam": "두산",
      "awayTeam": "키움",
      "platform": "티빙",
      "koreanCommentary": true
    },
    {
      "id": "tving-2026-04-08-18:30-KBO-한화-SSG",
      "date": "2026-04-08",
      "time": "18:30",
      "sport": "야구",
      "league": "KBO",
      "homeTeam": "SSG",
      "awayTeam": "한화",
      "platform": "티빙",
      "koreanCommentary": true
    },
    {
      "id": "kbs-sports-2026-04-08-18:45-진에어 2025-2026 V-리그 포",
      "date": "2026-04-08",
      "time": "18:45",
      "sport": "배구",
      "league": "V리그",
      "homeTeam": "현대캐피탈",
      "awayTeam": "대한항공",
      "platform": "KBS N SPORTS",
      "koreanCommentary": true
    },
    {
      "id": "spotvnow-2026-04-08-38193",
      "date": "2026-04-08",
      "time": "19:00",
      "sport": "농구",
      "league": "프로농구",
      "homeTeam": "KB스타즈",
      "awayTeam": "우리은행 우리WON",
      "platform": "SPOTV NOW",
      "koreanCommentary": true
    },
    {
      "id": "tvn-2026-04-08-19:00-2025-2026 LG전자 프로농구",
      "date": "2026-04-08",
      "time": "19:00",
      "sport": "농구",
      "league": "프로농구",
      "homeTeam": "KCC",
      "awayTeam": "DB",
      "platform": "tvN SPORTS",
      "koreanCommentary": true
    },
    {
      "id": "tving-2026-04-08-19:00-KBL-대구 한국가스공사-서울 삼성",
      "date": "2026-04-08",
      "time": "19:00",
      "sport": "농구",
      "league": "KBL",
      "homeTeam": "서울 삼성",
      "awayTeam": "대구 한국가스공사",
      "platform": "티빙",
      "koreanCommentary": true
    },
    {
      "id": "tving-2026-04-08-19:00-KBL-서울 SK-안양 정관장",
      "date": "2026-04-08",
      "time": "19:00",
      "sport": "농구",
      "league": "KBL",
      "homeTeam": "안양 정관장",
      "awayTeam": "서울 SK",
      "platform": "티빙",
      "koreanCommentary": true
    },
    {
      "id": "tving-2026-04-08-19:00-KBL-창원 LG-울산 현대모비스",
      "date": "2026-04-08",
      "time": "19:00",
      "sport": "농구",
      "league": "KBL",
      "homeTeam": "울산 현대모비스",
      "awayTeam": "창원 LG",
      "platform": "티빙",
      "koreanCommentary": true
    },
    {
      "id": "tving-2026-04-08-19:00-KBL-원주 DB-부산 KCC",
      "date": "2026-04-08",
      "time": "19:00",
      "sport": "농구",
      "league": "KBL",
      "homeTeam": "부산 KCC",
      "awayTeam": "원주 DB",
      "platform": "티빙",
      "koreanCommentary": true
    },
    {
      "id": "tving-2026-04-08-19:00-KBL-고양 소노-수원 KT",
      "date": "2026-04-08",
      "time": "19:00",
      "sport": "농구",
      "league": "KBL",
      "homeTeam": "수원 KT",
      "awayTeam": "고양 소노",
      "platform": "티빙",
      "koreanCommentary": true
    },
    {
      "id": "coupang-2026-04-08-19:00-ACL 2-감바 오사카-방콕 유나이티드",
      "date": "2026-04-08",
      "time": "19:00",
      "sport": "축구",
      "league": "AFC 챔피언스리그 2",
      "homeTeam": "감바 오사카",
      "awayTeam": "방콕 유나이티드",
      "platform": "쿠팡플레이",
      "koreanCommentary": true
    },
    {
      "id": "spotvnow-2026-04-08-38088",
      "date": "2026-04-08",
      "time": "19:05",
      "sport": "농구",
      "league": "프로농구",
      "homeTeam": "나가사키 벨카",
      "awayTeam": "산엔 네오피닉스",
      "platform": "SPOTV NOW",
      "koreanCommentary": true
    },
    {
      "id": "spotvnow-2026-04-08-38087",
      "date": "2026-04-08",
      "time": "19:05",
      "sport": "농구",
      "league": "프로농구",
      "homeTeam": "이바라키 로보츠",
      "awayTeam": "군마 크레인 썬더스",
      "platform": "SPOTV NOW",
      "koreanCommentary": "unknown"
    },
    {
      "id": "kbs-sports-2026-04-08-21:00-2026 신한 SOL KBO리그 삼성",
      "date": "2026-04-08",
      "time": "21:00",
      "sport": "야구",
      "league": "KBO",
      "homeTeam": "삼성",
      "awayTeam": "KIA",
      "platform": "KBS N SPORTS",
      "koreanCommentary": true
    },
    {
      "id": "sbs-sports-2026-04-08-21:50-2026 AFC U-20 여자 아시안",
      "date": "2026-04-08",
      "time": "21:50",
      "sport": "축구",
      "league": "AFC U-20 여자 아시안컵",
      "homeTeam": "대한민국",
      "awayTeam": "북한",
      "platform": "SBS Sports",
      "koreanCommentary": true
    },
    {
      "id": "coupang-2026-04-08-22:00-U20 여자 아시안컵-북한-대한민국",
      "date": "2026-04-08",
      "time": "22:00",
      "sport": "축구",
      "league": "AFC U20 여자 아시안컵",
      "homeTeam": "북한",
      "awayTeam": "대한민국",
      "platform": "쿠팡플레이",
      "koreanCommentary": true
    },
    {
      "id": "spotvnow-2026-04-09-38057",
      "date": "2026-04-09",
      "time": "01:35",
      "sport": "야구",
      "league": "MLB",
      "homeTeam": "샌디에이고 파드리스",
      "awayTeam": "피츠버그 파이리츠",
      "platform": "SPOTV NOW",
      "koreanCommentary": false
    },
    {
      "id": "spotvnow-2026-04-09-38029",
      "date": "2026-04-09",
      "time": "01:45",
      "sport": "축구",
      "league": "유로파리그",
      "homeTeam": "브라가",
      "awayTeam": "레알 베티스",
      "platform": "SPOTV NOW",
      "koreanCommentary": false
    },
    {
      "id": "spotvnow-2026-04-09-38027",
      "date": "2026-04-09",
      "time": "04:00",
      "sport": "축구",
      "league": "챔피언스리그",
      "homeTeam": "파리 생제르망",
      "awayTeam": "리버풀",
      "platform": "SPOTV NOW",
      "koreanCommentary": true
    },
    {
      "id": "spotvnow-2026-04-09-38028",
      "date": "2026-04-09",
      "time": "04:00",
      "sport": "축구",
      "league": "챔피언스리그",
      "homeTeam": "FC 바르셀로나",
      "awayTeam": "아틀레티코 마드리드",
      "platform": "SPOTV NOW",
      "koreanCommentary": true
    },
    {
      "id": "spotvnow-2026-04-09-38058",
      "date": "2026-04-09",
      "time": "04:07",
      "sport": "야구",
      "league": "MLB",
      "homeTeam": "LA 다저스",
      "awayTeam": "토론토 블루제이스",
      "platform": "SPOTV NOW",
      "koreanCommentary": true
    },
    {
      "id": "spotvnow-2026-04-09-38059",
      "date": "2026-04-09",
      "time": "04:45",
      "sport": "야구",
      "league": "MLB",
      "homeTeam": "필라델피아 필리스",
      "awayTeam": "샌프란시스코 자이언츠",
      "platform": "SPOTV NOW",
      "koreanCommentary": true
    },
    {
      "id": "coupang-2026-04-09-08:00-NBA-미네소타-올랜도",
      "date": "2026-04-09",
      "time": "08:00",
      "sport": "농구",
      "league": "NBA",
      "homeTeam": "미네소타",
      "awayTeam": "올랜도",
      "platform": "쿠팡플레이",
      "koreanCommentary": true
    },
    {
      "id": "coupang-2026-04-09-08:00-NBA-애틀랜타-클리블랜드",
      "date": "2026-04-09",
      "time": "08:00",
      "sport": "농구",
      "league": "NBA",
      "homeTeam": "애틀랜타",
      "awayTeam": "클리블랜드",
      "platform": "쿠팡플레이",
      "koreanCommentary": true
    },
    {
      "id": "spotvnow-2026-04-09-38060",
      "date": "2026-04-09",
      "time": "08:05",
      "sport": "야구",
      "league": "MLB",
      "homeTeam": "애슬레틱스",
      "awayTeam": "뉴욕 양키스",
      "platform": "SPOTV NOW",
      "koreanCommentary": true
    },
    {
      "id": "spotvnow-2026-04-09-38061",
      "date": "2026-04-09",
      "time": "08:10",
      "sport": "야구",
      "league": "MLB",
      "homeTeam": "애리조나 다이아몬드백스",
      "awayTeam": "뉴욕 메츠",
      "platform": "SPOTV NOW",
      "koreanCommentary": false
    },
    {
      "id": "spotvnow-2026-04-09-38062",
      "date": "2026-04-09",
      "time": "08:40",
      "sport": "야구",
      "league": "MLB",
      "homeTeam": "디트로이트 타이거스",
      "awayTeam": "미네소타 트윈스",
      "platform": "SPOTV NOW",
      "koreanCommentary": false
    },
    {
      "id": "coupang-2026-04-09-10:00-NBA-멤피스-덴버",
      "date": "2026-04-09",
      "time": "10:00",
      "sport": "농구",
      "league": "NBA",
      "homeTeam": "멤피스",
      "awayTeam": "덴버",
      "platform": "쿠팡플레이",
      "koreanCommentary": true
    },
    {
      "id": "coupang-2026-04-09-10:30-NBA-포틀랜드-샌안토니오",
      "date": "2026-04-09",
      "time": "10:30",
      "sport": "농구",
      "league": "NBA",
      "homeTeam": "포틀랜드",
      "awayTeam": "샌안토니오",
      "platform": "쿠팡플레이",
      "koreanCommentary": true
    },
    {
      "id": "coupang-2026-04-09-11:00-NBA-오클라호마시티-LA 클리퍼스",
      "date": "2026-04-09",
      "time": "11:00",
      "sport": "농구",
      "league": "NBA",
      "homeTeam": "오클라호마시티",
      "awayTeam": "LA 클리퍼스",
      "platform": "쿠팡플레이",
      "koreanCommentary": true
    },
    {
      "id": "coupang-2026-04-09-12:00-북중미 챔피언스컵-톨루카-LA 갤럭시",
      "date": "2026-04-09",
      "time": "12:00",
      "sport": "축구",
      "league": "북중미 챔피언스컵",
      "homeTeam": "톨루카",
      "awayTeam": "LA 갤럭시",
      "platform": "쿠팡플레이",
      "koreanCommentary": true
    },
    {
      "id": "tvn-2026-04-09-13:00-2026 메디힐 KBO 퓨처스리그",
      "date": "2026-04-09",
      "time": "13:00",
      "sport": "야구",
      "league": "KBO",
      "homeTeam": "KIA",
      "awayTeam": "삼성",
      "platform": "tvN SPORTS",
      "koreanCommentary": true
    },
    {
      "id": "kbs-sports-2026-04-09-18:10-2026 신한 SOL KBO리그 삼성",
      "date": "2026-04-09",
      "time": "18:10",
      "sport": "야구",
      "league": "KBO",
      "homeTeam": "삼성",
      "awayTeam": "KIA",
      "platform": "KBS N SPORTS",
      "koreanCommentary": true
    },
    {
      "id": "spotv-2026-04-09-18:15-2026 KBO리그 한화:SSG(문학",
      "date": "2026-04-09",
      "time": "18:15",
      "sport": "야구",
      "league": "KBO",
      "homeTeam": "한화",
      "awayTeam": "SSG",
      "platform": "SPOTV",
      "koreanCommentary": true
    },
    {
      "id": "spotv2-2026-04-09-18:15-2026 KBO리그 키움:두산 (잠실",
      "date": "2026-04-09",
      "time": "18:15",
      "sport": "야구",
      "league": "KBO",
      "homeTeam": "키움",
      "awayTeam": "두산",
      "platform": "SPOTV2",
      "koreanCommentary": true
    },
    {
      "id": "sbs-sports-2026-04-09-18:20-2026 KBO리그 LG:NC",
      "date": "2026-04-09",
      "time": "18:20",
      "sport": "야구",
      "league": "KBO",
      "homeTeam": "LG",
      "awayTeam": "NC",
      "platform": "SBS Sports",
      "koreanCommentary": true
    },
    {
      "id": "mbc-2026-04-09-18:30-2026 신한 SOL KBO리그",
      "date": "2026-04-09",
      "time": "18:30",
      "sport": "야구",
      "league": "KBO",
      "homeTeam": "KT",
      "awayTeam": "롯데",
      "platform": "MBC SPORTS+",
      "koreanCommentary": true
    },
    {
      "id": "tving-2026-04-09-18:30-KBO-한화-SSG",
      "date": "2026-04-09",
      "time": "18:30",
      "sport": "야구",
      "league": "KBO",
      "homeTeam": "SSG",
      "awayTeam": "한화",
      "platform": "티빙",
      "koreanCommentary": true
    },
    {
      "id": "tving-2026-04-09-18:30-KBO-KT-롯데",
      "date": "2026-04-09",
      "time": "18:30",
      "sport": "야구",
      "league": "KBO",
      "homeTeam": "롯데",
      "awayTeam": "KT",
      "platform": "티빙",
      "koreanCommentary": true
    },
    {
      "id": "tving-2026-04-09-18:30-KBO-LG-NC",
      "date": "2026-04-09",
      "time": "18:30",
      "sport": "야구",
      "league": "KBO",
      "homeTeam": "NC",
      "awayTeam": "LG",
      "platform": "티빙",
      "koreanCommentary": true
    },
    {
      "id": "tving-2026-04-09-18:30-KBO-삼성-KIA",
      "date": "2026-04-09",
      "time": "18:30",
      "sport": "야구",
      "league": "KBO",
      "homeTeam": "KIA",
      "awayTeam": "삼성",
      "platform": "티빙",
      "koreanCommentary": true
    },
    {
      "id": "tving-2026-04-09-18:30-KBO-키움-두산",
      "date": "2026-04-09",
      "time": "18:30",
      "sport": "야구",
      "league": "KBO",
      "homeTeam": "두산",
      "awayTeam": "키움",
      "platform": "티빙",
      "koreanCommentary": true
    },
    {
      "id": "spotvnow-2026-04-09-38194",
      "date": "2026-04-09",
      "time": "19:00",
      "sport": "농구",
      "league": "프로농구",
      "homeTeam": "하나은행",
      "awayTeam": "삼성생명 블루밍스",
      "platform": "SPOTV NOW",
      "koreanCommentary": true
    },
    {
      "id": "spotvnow-2026-04-10-38032",
      "date": "2026-04-10",
      "time": "01:45",
      "sport": "축구",
      "league": "컨퍼런스리그",
      "homeTeam": "라요 바예카노",
      "awayTeam": "AEK 아테네",
      "platform": "SPOTV NOW",
      "koreanCommentary": false
    },
    {
      "id": "spotvnow-2026-04-10-38063",
      "date": "2026-04-10",
      "time": "02:35",
      "sport": "야구",
      "league": "MLB",
      "homeTeam": "애슬레틱스",
      "awayTeam": "뉴욕 양키스",
      "platform": "SPOTV NOW",
      "koreanCommentary": true
    },
    {
      "id": "spotvnow-2026-04-10-38126",
      "date": "2026-04-10",
      "time": "04:00",
      "sport": "축구",
      "league": "유로파리그",
      "homeTeam": "SC 프라이부르크",
      "awayTeam": "셀타 비고",
      "platform": "SPOTV NOW",
      "koreanCommentary": false
    },
    {
      "id": "spotvnow-2026-04-10-38030",
      "date": "2026-04-10",
      "time": "04:00",
      "sport": "축구",
      "league": "유로파리그",
      "homeTeam": "볼로냐",
      "awayTeam": "아스톤 빌라",
      "platform": "SPOTV NOW",
      "koreanCommentary": true
    },
    {
      "id": "spotvnow-2026-04-10-38031",
      "date": "2026-04-10",
      "time": "04:00",
      "sport": "축구",
      "league": "유로파리그",
      "homeTeam": "FC 포르투",
      "awayTeam": "노팅엄 포레스트",
      "platform": "SPOTV NOW",
      "koreanCommentary": false
    },
    {
      "id": "spotvnow-2026-04-10-38033",
      "date": "2026-04-10",
      "time": "04:00",
      "sport": "축구",
      "league": "컨퍼런스리그",
      "homeTeam": "마인츠",
      "awayTeam": "RC 스트라스부르",
      "platform": "SPOTV NOW",
      "koreanCommentary": true
    },
    {
      "id": "spotvnow-2026-04-10-38034",
      "date": "2026-04-10",
      "time": "04:00",
      "sport": "축구",
      "league": "컨퍼런스리그",
      "homeTeam": "크리스탈 팰리스",
      "awayTeam": "피오렌티나",
      "platform": "SPOTV NOW",
      "koreanCommentary": false
    },
    {
      "id": "coupang-2026-04-10-08:00-NBA-마이애미-토론토",
      "date": "2026-04-10",
      "time": "08:00",
      "sport": "농구",
      "league": "NBA",
      "homeTeam": "마이애미",
      "awayTeam": "토론토",
      "platform": "쿠팡플레이",
      "koreanCommentary": true
    },
    {
      "id": "spotvnow-2026-04-10-38064",
      "date": "2026-04-10",
      "time": "08:10",
      "sport": "야구",
      "league": "MLB",
      "homeTeam": "애리조나 다이아몬드백스",
      "awayTeam": "뉴욕 메츠",
      "platform": "SPOTV NOW",
      "koreanCommentary": false
    },
    {
      "id": "spotvnow-2026-04-10-38065",
      "date": "2026-04-10",
      "time": "08:40",
      "sport": "야구",
      "league": "MLB",
      "homeTeam": "시카고 화이트삭스",
      "awayTeam": "캔자스시티 로열스",
      "platform": "SPOTV NOW",
      "koreanCommentary": false
    },
    {
      "id": "coupang-2026-04-10-09:00-NBA-필라델피아-휴스턴",
      "date": "2026-04-10",
      "time": "09:00",
      "sport": "농구",
      "league": "NBA",
      "homeTeam": "필라델피아",
      "awayTeam": "휴스턴",
      "platform": "쿠팡플레이",
      "koreanCommentary": true
    },
    {
      "id": "spotvnow-2026-04-10-38103",
      "date": "2026-04-10",
      "time": "10:00",
      "sport": "야구",
      "league": "고교야구",
      "homeTeam": "대전고",
      "awayTeam": "야탑고",
      "platform": "SPOTV NOW",
      "koreanCommentary": true
    },
    {
      "id": "spotvnow-2026-04-10-38066",
      "date": "2026-04-10",
      "time": "10:40",
      "sport": "야구",
      "league": "MLB",
      "homeTeam": "콜로라도 로키스",
      "awayTeam": "샌디에이고 파드리스",
      "platform": "SPOTV NOW",
      "koreanCommentary": true
    },
    {
      "id": "spotv-2026-04-10-18:15-2026 KBO리그 SSG:LG(잠실",
      "date": "2026-04-10",
      "time": "18:15",
      "sport": "야구",
      "league": "KBO",
      "homeTeam": "SSG",
      "awayTeam": "LG",
      "platform": "SPOTV",
      "koreanCommentary": true
    },
    {
      "id": "sbs-sports-2026-04-10-18:20-2026 KBO리그 두산:KT",
      "date": "2026-04-10",
      "time": "18:20",
      "sport": "야구",
      "league": "KBO",
      "homeTeam": "두산",
      "awayTeam": "KT",
      "platform": "SBS Sports",
      "koreanCommentary": true
    },
    {
      "id": "mbc-2026-04-10-18:30-2026 신한 SOL KBO리그",
      "date": "2026-04-10",
      "time": "18:30",
      "sport": "야구",
      "league": "KBO",
      "homeTeam": "NC",
      "awayTeam": "삼성",
      "platform": "MBC SPORTS+",
      "koreanCommentary": true
    },
    {
      "id": "tving-2026-04-10-18:30-KBO-KIA-한화",
      "date": "2026-04-10",
      "time": "18:30",
      "sport": "야구",
      "league": "KBO",
      "homeTeam": "한화",
      "awayTeam": "KIA",
      "platform": "티빙",
      "koreanCommentary": true
    },
    {
      "id": "tving-2026-04-10-18:30-KBO-롯데-키움",
      "date": "2026-04-10",
      "time": "18:30",
      "sport": "야구",
      "league": "KBO",
      "homeTeam": "키움",
      "awayTeam": "롯데",
      "platform": "티빙",
      "koreanCommentary": true
    },
    {
      "id": "tving-2026-04-10-18:30-KBO-NC-삼성",
      "date": "2026-04-10",
      "time": "18:30",
      "sport": "야구",
      "league": "KBO",
      "homeTeam": "삼성",
      "awayTeam": "NC",
      "platform": "티빙",
      "koreanCommentary": true
    },
    {
      "id": "tving-2026-04-10-18:30-KBO-두산-KT",
      "date": "2026-04-10",
      "time": "18:30",
      "sport": "야구",
      "league": "KBO",
      "homeTeam": "KT",
      "awayTeam": "두산",
      "platform": "티빙",
      "koreanCommentary": true
    },
    {
      "id": "tving-2026-04-10-18:30-KBO-SSG-LG",
      "date": "2026-04-10",
      "time": "18:30",
      "sport": "야구",
      "league": "KBO",
      "homeTeam": "LG",
      "awayTeam": "SSG",
      "platform": "티빙",
      "koreanCommentary": true
    },
    {
      "id": "kbs-sports-2026-04-10-18:45-진에어 2025-2026 V-리그 포",
      "date": "2026-04-10",
      "time": "18:45",
      "sport": "배구",
      "league": "V리그",
      "homeTeam": "대한항공",
      "awayTeam": "현대캐피탈",
      "platform": "KBS N SPORTS",
      "koreanCommentary": true
    },
    {
      "id": "spotvnow-2026-04-10-38195",
      "date": "2026-04-10",
      "time": "19:00",
      "sport": "농구",
      "league": "프로농구",
      "homeTeam": "KB스타즈",
      "awayTeam": "우리은행 우리WON",
      "platform": "SPOTV NOW",
      "koreanCommentary": true
    },
    {
      "id": "spotv2-2026-04-10-19:15-2026 KBO리그 두산:KT",
      "date": "2026-04-10",
      "time": "19:15",
      "sport": "야구",
      "league": "KBO",
      "homeTeam": "두산",
      "awayTeam": "KT",
      "platform": "SPOTV2",
      "koreanCommentary": true
    },
    {
      "id": "kbs-sports-2026-04-10-21:00-2026 신한 SOL KBO리그 롯데",
      "date": "2026-04-10",
      "time": "21:00",
      "sport": "야구",
      "league": "KBO",
      "homeTeam": "롯데",
      "awayTeam": "키움",
      "platform": "KBS N SPORTS",
      "koreanCommentary": true
    },
    {
      "id": "coupang-2026-04-11-01:30-분데스리가 2-카를스루어-빌레펠트",
      "date": "2026-04-11",
      "time": "01:30",
      "sport": "축구",
      "league": "분데스리가 2",
      "homeTeam": "카를스루어",
      "awayTeam": "빌레펠트",
      "platform": "쿠팡플레이",
      "koreanCommentary": true
    },
    {
      "id": "coupang-2026-04-11-02:00-리그 1-파리 FC-모나코",
      "date": "2026-04-11",
      "time": "02:00",
      "sport": "축구",
      "league": "리그 1",
      "homeTeam": "파리 FC",
      "awayTeam": "모나코",
      "platform": "쿠팡플레이",
      "koreanCommentary": true
    },
    {
      "id": "coupang-2026-04-11-02:00-쉬페르리그-베식타시-안탈리아스포르",
      "date": "2026-04-11",
      "time": "02:00",
      "sport": "축구",
      "league": "쉬페르리그",
      "homeTeam": "베식타시",
      "awayTeam": "안탈리아스포르",
      "platform": "쿠팡플레이",
      "koreanCommentary": true
    },
    {
      "id": "spotvnow-2026-04-11-38067",
      "date": "2026-04-11",
      "time": "03:20",
      "sport": "야구",
      "league": "MLB",
      "homeTeam": "피츠버그 파이리츠",
      "awayTeam": "시카고 컵스",
      "platform": "SPOTV NOW",
      "koreanCommentary": false
    },
    {
      "id": "coupang-2026-04-11-03:30-분데스리가-아우크스부르크-호펜하임",
      "date": "2026-04-11",
      "time": "03:30",
      "sport": "축구",
      "league": "분데스리가",
      "homeTeam": "아우크스부르크",
      "awayTeam": "호펜하임",
      "platform": "쿠팡플레이",
      "koreanCommentary": true
    },
    {
      "id": "spotvnow-2026-04-11-38035",
      "date": "2026-04-11",
      "time": "03:45",
      "sport": "축구",
      "league": "세리에A",
      "homeTeam": "AS 로마",
      "awayTeam": "피사",
      "platform": "SPOTV NOW",
      "koreanCommentary": false
    },
    {
      "id": "coupang-2026-04-11-04:00-프리미어리그-웨스트햄-울버햄튼",
      "date": "2026-04-11",
      "time": "04:00",
      "sport": "축구",
      "league": "프리미어리그",
      "homeTeam": "웨스트햄",
      "awayTeam": "울버햄튼",
      "platform": "쿠팡플레이",
      "koreanCommentary": true
    },
    {
      "id": "coupang-2026-04-11-04:00-라리가-레알 마드리드-지로나",
      "date": "2026-04-11",
      "time": "04:00",
      "sport": "축구",
      "league": "라리가",
      "homeTeam": "레알 마드리드",
      "awayTeam": "지로나",
      "platform": "쿠팡플레이",
      "koreanCommentary": true
    },
    {
      "id": "coupang-2026-04-11-04:05-리그 1-마르세유-메스",
      "date": "2026-04-11",
      "time": "04:05",
      "sport": "축구",
      "league": "리그 1",
      "homeTeam": "마르세유",
      "awayTeam": "메스",
      "platform": "쿠팡플레이",
      "koreanCommentary": true
    },
    {
      "id": "apple-tv-2026-04-11-07:45-MLB-LAA-CIN",
      "date": "2026-04-11",
      "time": "07:45",
      "sport": "야구",
      "league": "MLB",
      "homeTeam": "신시내티 레즈",
      "awayTeam": "로스앤젤레스 에인절스",
      "platform": "Apple TV+",
      "koreanCommentary": false
    },
    {
      "id": "spotv-2026-04-11-07:55-2026 메이저리그 뉴욕 양키스:탬파",
      "date": "2026-04-11",
      "time": "07:55",
      "sport": "야구",
      "league": "MLB",
      "homeTeam": "뉴욕 양키스",
      "awayTeam": "탬파베이",
      "platform": "SPOTV",
      "koreanCommentary": "unknown"
    },
    {
      "id": "spotvnow-2026-04-11-38127",
      "date": "2026-04-11",
      "time": "08:07",
      "sport": "야구",
      "league": "MLB",
      "homeTeam": "미네소타 트윈스",
      "awayTeam": "토론토 블루제이스",
      "platform": "SPOTV NOW",
      "koreanCommentary": false
    },
    {
      "id": "spotvnow-2026-04-11-38069",
      "date": "2026-04-11",
      "time": "08:10",
      "sport": "야구",
      "league": "MLB",
      "homeTeam": "뉴욕 양키스",
      "awayTeam": "탬파베이 레이스",
      "platform": "SPOTV NOW",
      "koreanCommentary": true
    },
    {
      "id": "spotvnow-2026-04-11-38071",
      "date": "2026-04-11",
      "time": "08:15",
      "sport": "야구",
      "league": "MLB",
      "homeTeam": "클리블랜드 가디언스",
      "awayTeam": "애틀랜타 브레이브스",
      "platform": "SPOTV NOW",
      "koreanCommentary": false
    },
    {
      "id": "spotvnow-2026-04-11-38070",
      "date": "2026-04-11",
      "time": "08:15",
      "sport": "야구",
      "league": "MLB",
      "homeTeam": "샌프란시스코 자이언츠",
      "awayTeam": "볼티모어 오리올스",
      "platform": "SPOTV NOW",
      "koreanCommentary": true
    },
    {
      "id": "apple-tv-2026-04-11-08:15-MLB-SF-BAL",
      "date": "2026-04-11",
      "time": "08:15",
      "sport": "야구",
      "league": "MLB",
      "homeTeam": "볼티모어 오리올스",
      "awayTeam": "샌프란시스코 자이언츠",
      "platform": "Apple TV+",
      "koreanCommentary": false
    },
    {
      "id": "coupang-2026-04-11-10:00-NBA-오클라호마시티-덴버",
      "date": "2026-04-11",
      "time": "10:00",
      "sport": "농구",
      "league": "NBA",
      "homeTeam": "오클라호마시티",
      "awayTeam": "덴버",
      "platform": "쿠팡플레이",
      "koreanCommentary": true
    },
    {
      "id": "spotvnow-2026-04-11-38073",
      "date": "2026-04-11",
      "time": "10:40",
      "sport": "야구",
      "league": "MLB",
      "homeTeam": "휴스턴 애스트로스",
      "awayTeam": "시애틀 매리너스",
      "platform": "SPOTV NOW",
      "koreanCommentary": false
    },
    {
      "id": "spotvnow-2026-04-11-38072",
      "date": "2026-04-11",
      "time": "10:40",
      "sport": "야구",
      "league": "MLB",
      "homeTeam": "콜로라도 로키스",
      "awayTeam": "샌디에이고 파드리스",
      "platform": "SPOTV NOW",
      "koreanCommentary": true
    },
    {
      "id": "spotvnow-2026-04-11-38074",
      "date": "2026-04-11",
      "time": "11:10",
      "sport": "야구",
      "league": "MLB",
      "homeTeam": "텍사스 레인저스",
      "awayTeam": "LA 다저스",
      "platform": "SPOTV NOW",
      "koreanCommentary": true
    },
    {
      "id": "coupang-2026-04-11-11:30-NBA-피닉스-LA 레이커스",
      "date": "2026-04-11",
      "time": "11:30",
      "sport": "농구",
      "league": "NBA",
      "homeTeam": "피닉스",
      "awayTeam": "LA 레이커스",
      "platform": "쿠팡플레이",
      "koreanCommentary": true
    },
    {
      "id": "tving-2026-04-11-14:00-KBO-KIA-한화",
      "date": "2026-04-11",
      "time": "14:00",
      "sport": "야구",
      "league": "KBO",
      "homeTeam": "한화",
      "awayTeam": "KIA",
      "platform": "티빙",
      "koreanCommentary": true
    },
    {
      "id": "coupang-2026-04-11-14:00-K리그1-서울-전북",
      "date": "2026-04-11",
      "time": "14:00",
      "sport": "축구",
      "league": "K리그1",
      "homeTeam": "서울",
      "awayTeam": "전북",
      "platform": "쿠팡플레이",
      "koreanCommentary": true
    },
    {
      "id": "coupang-2026-04-11-14:00-K리그1-포항-제주",
      "date": "2026-04-11",
      "time": "14:00",
      "sport": "축구",
      "league": "K리그1",
      "homeTeam": "포항",
      "awayTeam": "제주",
      "platform": "쿠팡플레이",
      "koreanCommentary": true
    },
    {
      "id": "coupang-2026-04-11-14:00-K리그2-수원FC-대구",
      "date": "2026-04-11",
      "time": "14:00",
      "sport": "축구",
      "league": "K리그2",
      "homeTeam": "수원FC",
      "awayTeam": "대구",
      "platform": "쿠팡플레이",
      "koreanCommentary": true
    },
    {
      "id": "coupang-2026-04-11-14:00-K리그2-부산-용인",
      "date": "2026-04-11",
      "time": "14:00",
      "sport": "축구",
      "league": "K리그2",
      "homeTeam": "부산",
      "awayTeam": "용인",
      "platform": "쿠팡플레이",
      "koreanCommentary": true
    },
    {
      "id": "spotvnow-2026-04-11-38089",
      "date": "2026-04-11",
      "time": "15:05",
      "sport": "농구",
      "league": "프로농구",
      "homeTeam": "레반가 홋카이도",
      "awayTeam": "나가사키 벨카",
      "platform": "SPOTV NOW",
      "koreanCommentary": true
    },
    {
      "id": "spotvnow-2026-04-11-38196",
      "date": "2026-04-11",
      "time": "16:00",
      "sport": "농구",
      "league": "프로농구",
      "homeTeam": "하나은행",
      "awayTeam": "삼성생명 블루밍스",
      "platform": "SPOTV NOW",
      "koreanCommentary": true
    },
    {
      "id": "coupang-2026-04-11-16:30-K리그1-인천-울산",
      "date": "2026-04-11",
      "time": "16:30",
      "sport": "축구",
      "league": "K리그1",
      "homeTeam": "인천",
      "awayTeam": "울산",
      "platform": "쿠팡플레이",
      "koreanCommentary": true
    },
    {
      "id": "coupang-2026-04-11-16:30-K리그1-광주-부천",
      "date": "2026-04-11",
      "time": "16:30",
      "sport": "축구",
      "league": "K리그1",
      "homeTeam": "광주",
      "awayTeam": "부천",
      "platform": "쿠팡플레이",
      "koreanCommentary": true
    },
    {
      "id": "coupang-2026-04-11-16:30-K리그2-파주-서울E",
      "date": "2026-04-11",
      "time": "16:30",
      "sport": "축구",
      "league": "K리그2",
      "homeTeam": "파주",
      "awayTeam": "서울E",
      "platform": "쿠팡플레이",
      "koreanCommentary": true
    },
    {
      "id": "coupang-2026-04-11-16:30-K리그2-화성-전남",
      "date": "2026-04-11",
      "time": "16:30",
      "sport": "축구",
      "league": "K리그2",
      "homeTeam": "화성",
      "awayTeam": "전남",
      "platform": "쿠팡플레이",
      "koreanCommentary": true
    },
    {
      "id": "kbs-sports-2026-04-11-16:40-2026 신한 SOL KBO리그 롯데",
      "date": "2026-04-11",
      "time": "16:40",
      "sport": "야구",
      "league": "KBO",
      "homeTeam": "롯데",
      "awayTeam": "키움",
      "platform": "KBS N SPORTS",
      "koreanCommentary": true
    },
    {
      "id": "spotv-2026-04-11-16:45-2026 KBO리그 SSG:LG(잠실",
      "date": "2026-04-11",
      "time": "16:45",
      "sport": "야구",
      "league": "KBO",
      "homeTeam": "SSG",
      "awayTeam": "LG",
      "platform": "SPOTV",
      "koreanCommentary": true
    },
    {
      "id": "spotv2-2026-04-11-16:45-2026 KBO리그 두산:KT",
      "date": "2026-04-11",
      "time": "16:45",
      "sport": "야구",
      "league": "KBO",
      "homeTeam": "두산",
      "awayTeam": "KT",
      "platform": "SPOTV2",
      "koreanCommentary": true
    },
    {
      "id": "sbs-sports-2026-04-11-16:50-2026 KBO리그 두산:KT",
      "date": "2026-04-11",
      "time": "16:50",
      "sport": "야구",
      "league": "KBO",
      "homeTeam": "두산",
      "awayTeam": "KT",
      "platform": "SBS Sports",
      "koreanCommentary": true
    },
    {
      "id": "mbc-2026-04-11-17:00-2026 신한 SOL KBO리그",
      "date": "2026-04-11",
      "time": "17:00",
      "sport": "야구",
      "league": "KBO",
      "homeTeam": "NC",
      "awayTeam": "삼성",
      "platform": "MBC SPORTS+",
      "koreanCommentary": true
    },
    {
      "id": "tving-2026-04-11-17:00-KBO-롯데-키움",
      "date": "2026-04-11",
      "time": "17:00",
      "sport": "야구",
      "league": "KBO",
      "homeTeam": "키움",
      "awayTeam": "롯데",
      "platform": "티빙",
      "koreanCommentary": true
    },
    {
      "id": "tving-2026-04-11-17:00-KBO-NC-삼성",
      "date": "2026-04-11",
      "time": "17:00",
      "sport": "야구",
      "league": "KBO",
      "homeTeam": "삼성",
      "awayTeam": "NC",
      "platform": "티빙",
      "koreanCommentary": true
    },
    {
      "id": "tving-2026-04-11-17:00-KBO-두산-KT",
      "date": "2026-04-11",
      "time": "17:00",
      "sport": "야구",
      "league": "KBO",
      "homeTeam": "KT",
      "awayTeam": "두산",
      "platform": "티빙",
      "koreanCommentary": true
    },
    {
      "id": "tving-2026-04-11-17:00-KBO-SSG-LG",
      "date": "2026-04-11",
      "time": "17:00",
      "sport": "야구",
      "league": "KBO",
      "homeTeam": "LG",
      "awayTeam": "SSG",
      "platform": "티빙",
      "koreanCommentary": true
    },
    {
      "id": "spotvnow-2026-04-11-38090",
      "date": "2026-04-11",
      "time": "18:05",
      "sport": "농구",
      "league": "프로농구",
      "homeTeam": "류큐 골든 킹스",
      "awayTeam": "이바라키 로보츠",
      "platform": "SPOTV NOW",
      "koreanCommentary": "unknown"
    },
    {
      "id": "coupang-2026-04-11-20:30-프리미어리그-아스날-본머스",
      "date": "2026-04-11",
      "time": "20:30",
      "sport": "축구",
      "league": "프리미어리그",
      "homeTeam": "아스날",
      "awayTeam": "본머스",
      "platform": "쿠팡플레이",
      "koreanCommentary": true
    },
    {
      "id": "coupang-2026-04-11-21:00-라리가-레알 소시에다드-알라베스",
      "date": "2026-04-11",
      "time": "21:00",
      "sport": "축구",
      "league": "라리가",
      "homeTeam": "레알 소시에다드",
      "awayTeam": "알라베스",
      "platform": "쿠팡플레이",
      "koreanCommentary": true
    },
    {
      "id": "spotvnow-2026-04-11-38037",
      "date": "2026-04-11",
      "time": "22:00",
      "sport": "축구",
      "league": "세리에A",
      "homeTeam": "토리노",
      "awayTeam": "헬라스 베로나",
      "platform": "SPOTV NOW",
      "koreanCommentary": false
    },
    {
      "id": "spotvnow-2026-04-11-38036",
      "date": "2026-04-11",
      "time": "22:00",
      "sport": "축구",
      "league": "세리에A",
      "homeTeam": "칼리아리 칼초",
      "awayTeam": "크레모네세",
      "platform": "SPOTV NOW",
      "koreanCommentary": false
    },
    {
      "id": "coupang-2026-04-11-22:30-분데스리가-하이덴하임-우니온 베를린",
      "date": "2026-04-11",
      "time": "22:30",
      "sport": "축구",
      "league": "분데스리가",
      "homeTeam": "하이덴하임",
      "awayTeam": "우니온 베를린",
      "platform": "쿠팡플레이",
      "koreanCommentary": true
    },
    {
      "id": "coupang-2026-04-11-22:30-분데스리가-볼프스부르크-프랑크푸르트",
      "date": "2026-04-11",
      "time": "22:30",
      "sport": "축구",
      "league": "분데스리가",
      "homeTeam": "볼프스부르크",
      "awayTeam": "프랑크푸르트",
      "platform": "쿠팡플레이",
      "koreanCommentary": true
    },
    {
      "id": "coupang-2026-04-11-22:30-분데스리가-라이프치히-묀헨글라트바흐",
      "date": "2026-04-11",
      "time": "22:30",
      "sport": "축구",
      "league": "분데스리가",
      "homeTeam": "라이프치히",
      "awayTeam": "묀헨글라트바흐",
      "platform": "쿠팡플레이",
      "koreanCommentary": true
    },
    {
      "id": "coupang-2026-04-11-22:30-분데스리가-도르트문트-레버쿠젠",
      "date": "2026-04-11",
      "time": "22:30",
      "sport": "축구",
      "league": "분데스리가",
      "homeTeam": "도르트문트",
      "awayTeam": "레버쿠젠",
      "platform": "쿠팡플레이",
      "koreanCommentary": true
    },
    {
      "id": "coupang-2026-04-11-23:00-프리미어리그-번리-브라이튼",
      "date": "2026-04-11",
      "time": "23:00",
      "sport": "축구",
      "league": "프리미어리그",
      "homeTeam": "번리",
      "awayTeam": "브라이튼",
      "platform": "쿠팡플레이",
      "koreanCommentary": true
    },
    {
      "id": "coupang-2026-04-11-23:00-프리미어리그-브렌트포드-에버턴",
      "date": "2026-04-11",
      "time": "23:00",
      "sport": "축구",
      "league": "프리미어리그",
      "homeTeam": "브렌트포드",
      "awayTeam": "에버턴",
      "platform": "쿠팡플레이",
      "koreanCommentary": true
    },
    {
      "id": "coupang-2026-04-11-23:15-라리가-엘체-발렌시아",
      "date": "2026-04-11",
      "time": "23:15",
      "sport": "축구",
      "league": "라리가",
      "homeTeam": "엘체",
      "awayTeam": "발렌시아",
      "platform": "쿠팡플레이",
      "koreanCommentary": true
    },
    {
      "id": "spotvnow-2026-04-12-38038",
      "date": "2026-04-12",
      "time": "01:00",
      "sport": "축구",
      "league": "세리에A",
      "homeTeam": "AC 밀란",
      "awayTeam": "우디네세 칼초",
      "platform": "SPOTV NOW",
      "koreanCommentary": false
    },
    {
      "id": "coupang-2026-04-12-01:30-프리미어리그-리버풀-풀럼",
      "date": "2026-04-12",
      "time": "01:30",
      "sport": "축구",
      "league": "프리미어리그",
      "homeTeam": "리버풀",
      "awayTeam": "풀럼",
      "platform": "쿠팡플레이",
      "koreanCommentary": true
    },
    {
      "id": "coupang-2026-04-12-01:30-분데스리가-장크트파울리-바이에른 뮌헨",
      "date": "2026-04-12",
      "time": "01:30",
      "sport": "축구",
      "league": "분데스리가",
      "homeTeam": "장크트파울리",
      "awayTeam": "바이에른 뮌헨",
      "platform": "쿠팡플레이",
      "koreanCommentary": true
    },
    {
      "id": "coupang-2026-04-12-01:30-라리가-바르셀로나-에스파뇰",
      "date": "2026-04-12",
      "time": "01:30",
      "sport": "축구",
      "league": "라리가",
      "homeTeam": "바르셀로나",
      "awayTeam": "에스파뇰",
      "platform": "쿠팡플레이",
      "koreanCommentary": true
    },
    {
      "id": "coupang-2026-04-12-02:00-리그 1-오세르-낭트",
      "date": "2026-04-12",
      "time": "02:00",
      "sport": "축구",
      "league": "리그 1",
      "homeTeam": "오세르",
      "awayTeam": "낭트",
      "platform": "쿠팡플레이",
      "koreanCommentary": true
    },
    {
      "id": "spotvnow-2026-04-12-38128",
      "date": "2026-04-12",
      "time": "02:05",
      "sport": "야구",
      "league": "MLB",
      "homeTeam": "애리조나 다이아몬드백스",
      "awayTeam": "필라델피아 필리스",
      "platform": "SPOTV NOW",
      "koreanCommentary": false
    },
    {
      "id": "spotvnow-2026-04-12-38039",
      "date": "2026-04-12",
      "time": "03:45",
      "sport": "축구",
      "league": "세리에A",
      "homeTeam": "아탈란타",
      "awayTeam": "유벤투스",
      "platform": "SPOTV NOW",
      "koreanCommentary": true
    },
    {
      "id": "coupang-2026-04-12-04:00-라리가-세비야-AT.마드리드",
      "date": "2026-04-12",
      "time": "04:00",
      "sport": "축구",
      "league": "라리가",
      "homeTeam": "세비야",
      "awayTeam": "AT.마드리드",
      "platform": "쿠팡플레이",
      "koreanCommentary": true
    },
    {
      "id": "coupang-2026-04-12-04:05-리그 1-스타드 렌-앙제",
      "date": "2026-04-12",
      "time": "04:05",
      "sport": "축구",
      "league": "리그 1",
      "homeTeam": "스타드 렌",
      "awayTeam": "앙제",
      "platform": "쿠팡플레이",
      "koreanCommentary": true
    },
    {
      "id": "coupang-2026-04-12-05:00-MLS-포틀랜드-LAFC",
      "date": "2026-04-12",
      "time": "05:00",
      "sport": "축구",
      "league": "MLS",
      "homeTeam": "포틀랜드",
      "awayTeam": "LAFC",
      "platform": "쿠팡플레이",
      "koreanCommentary": true
    },
    {
      "id": "spotvnow-2026-04-12-38129",
      "date": "2026-04-12",
      "time": "05:10",
      "sport": "야구",
      "league": "MLB",
      "homeTeam": "애슬레틱스",
      "awayTeam": "뉴욕 메츠",
      "platform": "SPOTV NOW",
      "koreanCommentary": false
    },
    {
      "id": "apple-tv-2026-04-12-05:30-MLS-LAFC-POR",
      "date": "2026-04-12",
      "time": "05:30",
      "sport": "축구",
      "league": "MLS",
      "homeTeam": "포틀랜드 팀버스",
      "awayTeam": "로스앤젤레스 FC",
      "platform": "Apple TV+",
      "koreanCommentary": false
    },
    {
      "id": "spotvnow-2026-04-12-38076",
      "date": "2026-04-12",
      "time": "07:10",
      "sport": "야구",
      "league": "MLB",
      "homeTeam": "뉴욕 양키스",
      "awayTeam": "탬파베이 레이스",
      "platform": "SPOTV NOW",
      "koreanCommentary": true
    },
    {
      "id": "spotvnow-2026-04-12-38077",
      "date": "2026-04-12",
      "time": "08:15",
      "sport": "야구",
      "league": "MLB",
      "homeTeam": "샌프란시스코 자이언츠",
      "awayTeam": "볼티모어 오리올스",
      "platform": "SPOTV NOW",
      "koreanCommentary": true
    },
    {
      "id": "apple-tv-2026-04-12-08:30-MLS-RBNY-MIA",
      "date": "2026-04-12",
      "time": "08:30",
      "sport": "축구",
      "league": "MLS",
      "homeTeam": "인터 마이애미 CF",
      "awayTeam": "레드불 뉴욕",
      "platform": "Apple TV+",
      "koreanCommentary": false
    },
    {
      "id": "apple-tv-2026-04-12-08:30-MLS-NSH-CLT",
      "date": "2026-04-12",
      "time": "08:30",
      "sport": "축구",
      "league": "MLS",
      "homeTeam": "샬럿 FC",
      "awayTeam": "내슈빌 SC",
      "platform": "Apple TV+",
      "koreanCommentary": false
    },
    {
      "id": "spotvnow-2026-04-12-38078",
      "date": "2026-04-12",
      "time": "09:40",
      "sport": "야구",
      "league": "MLB",
      "homeTeam": "콜로라도 로키스",
      "awayTeam": "샌디에이고 파드리스",
      "platform": "SPOTV NOW",
      "koreanCommentary": true
    },
    {
      "id": "spotvnow-2026-04-12-38079",
      "date": "2026-04-12",
      "time": "10:10",
      "sport": "야구",
      "league": "MLB",
      "homeTeam": "텍사스 레인저스",
      "awayTeam": "LA 다저스",
      "platform": "SPOTV NOW",
      "koreanCommentary": true
    },
    {
      "id": "spotvnow-2026-04-12-38080",
      "date": "2026-04-12",
      "time": "10:40",
      "sport": "야구",
      "league": "MLB",
      "homeTeam": "휴스턴 애스트로스",
      "awayTeam": "시애틀 매리너스",
      "platform": "SPOTV NOW",
      "koreanCommentary": false
    },
    {
      "id": "apple-tv-2026-04-12-11:30-MLS-MIN-SD",
      "date": "2026-04-12",
      "time": "11:30",
      "sport": "축구",
      "league": "MLS",
      "homeTeam": "샌디에이고 FC",
      "awayTeam": "미네소타 유나이티드",
      "platform": "Apple TV+",
      "koreanCommentary": false
    },
    {
      "id": "kbs-sports-2026-04-12-13:40-2026 신한 SOL KBO리그 롯데",
      "date": "2026-04-12",
      "time": "13:40",
      "sport": "야구",
      "league": "KBO",
      "homeTeam": "롯데",
      "awayTeam": "키움",
      "platform": "KBS N SPORTS",
      "koreanCommentary": true
    },
    {
      "id": "spotv-2026-04-12-13:45-2026 KBO리그 SSG:LG(잠실",
      "date": "2026-04-12",
      "time": "13:45",
      "sport": "야구",
      "league": "KBO",
      "homeTeam": "SSG",
      "awayTeam": "LG",
      "platform": "SPOTV",
      "koreanCommentary": true
    },
    {
      "id": "spotv2-2026-04-12-13:45-2026 KBO리그 두산:KT",
      "date": "2026-04-12",
      "time": "13:45",
      "sport": "야구",
      "league": "KBO",
      "homeTeam": "두산",
      "awayTeam": "KT",
      "platform": "SPOTV2",
      "koreanCommentary": true
    },
    {
      "id": "sbs-sports-2026-04-12-13:50-2026 KBO리그 두산:KT",
      "date": "2026-04-12",
      "time": "13:50",
      "sport": "야구",
      "league": "KBO",
      "homeTeam": "두산",
      "awayTeam": "KT",
      "platform": "SBS Sports",
      "koreanCommentary": true
    },
    {
      "id": "mbc-2026-04-12-14:00-2026 신한 SOL KBO리그",
      "date": "2026-04-12",
      "time": "14:00",
      "sport": "야구",
      "league": "KBO",
      "homeTeam": "NC",
      "awayTeam": "삼성",
      "platform": "MBC SPORTS+",
      "koreanCommentary": true
    },
    {
      "id": "tving-2026-04-12-14:00-KBO-KIA-한화",
      "date": "2026-04-12",
      "time": "14:00",
      "sport": "야구",
      "league": "KBO",
      "homeTeam": "한화",
      "awayTeam": "KIA",
      "platform": "티빙",
      "koreanCommentary": true
    },
    {
      "id": "tving-2026-04-12-14:00-KBO-롯데-키움",
      "date": "2026-04-12",
      "time": "14:00",
      "sport": "야구",
      "league": "KBO",
      "homeTeam": "키움",
      "awayTeam": "롯데",
      "platform": "티빙",
      "koreanCommentary": true
    },
    {
      "id": "tving-2026-04-12-14:00-KBO-NC-삼성",
      "date": "2026-04-12",
      "time": "14:00",
      "sport": "야구",
      "league": "KBO",
      "homeTeam": "삼성",
      "awayTeam": "NC",
      "platform": "티빙",
      "koreanCommentary": true
    },
    {
      "id": "tving-2026-04-12-14:00-KBO-두산-KT",
      "date": "2026-04-12",
      "time": "14:00",
      "sport": "야구",
      "league": "KBO",
      "homeTeam": "KT",
      "awayTeam": "두산",
      "platform": "티빙",
      "koreanCommentary": true
    },
    {
      "id": "tving-2026-04-12-14:00-KBO-SSG-LG",
      "date": "2026-04-12",
      "time": "14:00",
      "sport": "야구",
      "league": "KBO",
      "homeTeam": "LG",
      "awayTeam": "SSG",
      "platform": "티빙",
      "koreanCommentary": true
    },
    {
      "id": "coupang-2026-04-12-14:00-K리그1-대전-강원",
      "date": "2026-04-12",
      "time": "14:00",
      "sport": "축구",
      "league": "K리그1",
      "homeTeam": "대전",
      "awayTeam": "강원",
      "platform": "쿠팡플레이",
      "koreanCommentary": true
    },
    {
      "id": "coupang-2026-04-12-14:00-K리그2-수원-김포",
      "date": "2026-04-12",
      "time": "14:00",
      "sport": "축구",
      "league": "K리그2",
      "homeTeam": "수원",
      "awayTeam": "김포",
      "platform": "쿠팡플레이",
      "koreanCommentary": true
    },
    {
      "id": "coupang-2026-04-12-14:00-K리그2-천안-충북청주",
      "date": "2026-04-12",
      "time": "14:00",
      "sport": "축구",
      "league": "K리그2",
      "homeTeam": "천안",
      "awayTeam": "충북청주",
      "platform": "쿠팡플레이",
      "koreanCommentary": true
    },
    {
      "id": "spotvnow-2026-04-12-38091",
      "date": "2026-04-12",
      "time": "14:05",
      "sport": "농구",
      "league": "프로농구",
      "homeTeam": "레반가 홋카이도",
      "awayTeam": "나가사키 벨카",
      "platform": "SPOTV NOW",
      "koreanCommentary": true
    },
    {
      "id": "spotvnow-2026-04-12-38197",
      "date": "2026-04-12",
      "time": "16:00",
      "sport": "농구",
      "league": "프로농구",
      "homeTeam": "우리은행 우리WON",
      "awayTeam": "KB스타즈",
      "platform": "SPOTV NOW",
      "koreanCommentary": true
    },
    {
      "id": "coupang-2026-04-12-16:30-K리그1-김천-안양",
      "date": "2026-04-12",
      "time": "16:30",
      "sport": "축구",
      "league": "K리그1",
      "homeTeam": "김천",
      "awayTeam": "안양",
      "platform": "쿠팡플레이",
      "koreanCommentary": true
    },
    {
      "id": "coupang-2026-04-12-16:30-K리그2-충남아산-김해",
      "date": "2026-04-12",
      "time": "16:30",
      "sport": "축구",
      "league": "K리그2",
      "homeTeam": "충남아산",
      "awayTeam": "김해",
      "platform": "쿠팡플레이",
      "koreanCommentary": true
    },
    {
      "id": "coupang-2026-04-12-16:30-K리그2-성남-안산",
      "date": "2026-04-12",
      "time": "16:30",
      "sport": "축구",
      "league": "K리그2",
      "homeTeam": "성남",
      "awayTeam": "안산",
      "platform": "쿠팡플레이",
      "koreanCommentary": true
    },
    {
      "id": "spotv2-2026-04-12-17:30-25-26 여자프로농구 플레이오프 3",
      "date": "2026-04-12",
      "time": "17:30",
      "sport": "농구",
      "league": "프로농구",
      "homeTeam": "전 우리은행",
      "awayTeam": "KB스타즈",
      "platform": "SPOTV2",
      "koreanCommentary": true
    },
    {
      "id": "spotvnow-2026-04-12-38092",
      "date": "2026-04-12",
      "time": "18:05",
      "sport": "농구",
      "league": "프로농구",
      "homeTeam": "류큐 골든 킹스",
      "awayTeam": "이바라키 로보츠",
      "platform": "SPOTV NOW",
      "koreanCommentary": "unknown"
    },
    {
      "id": "spotvnow-2026-04-12-38040",
      "date": "2026-04-12",
      "time": "19:30",
      "sport": "축구",
      "league": "세리에A",
      "homeTeam": "제노아",
      "awayTeam": "사수올로 칼초",
      "platform": "SPOTV NOW",
      "koreanCommentary": false
    },
    {
      "id": "coupang-2026-04-12-20:00-EFL 챔피언십-버밍엄-렉섬",
      "date": "2026-04-12",
      "time": "20:00",
      "sport": "축구",
      "league": "EFL 챔피언십",
      "homeTeam": "버밍엄",
      "awayTeam": "렉섬",
      "platform": "쿠팡플레이",
      "koreanCommentary": true
    },
    {
      "id": "coupang-2026-04-12-21:00-라리가-오사수나-레알 베티스",
      "date": "2026-04-12",
      "time": "21:00",
      "sport": "축구",
      "league": "라리가",
      "homeTeam": "오사수나",
      "awayTeam": "레알 베티스",
      "platform": "쿠팡플레이",
      "koreanCommentary": true
    },
    {
      "id": "coupang-2026-04-12-21:30-에레디비시-네이메헨-페예노르트",
      "date": "2026-04-12",
      "time": "21:30",
      "sport": "축구",
      "league": "에레디비시",
      "homeTeam": "네이메헨",
      "awayTeam": "페예노르트",
      "platform": "쿠팡플레이",
      "koreanCommentary": true
    },
    {
      "id": "spotvnow-2026-04-12-38041",
      "date": "2026-04-12",
      "time": "22:00",
      "sport": "축구",
      "league": "세리에A",
      "homeTeam": "파르마 칼초",
      "awayTeam": "나폴리",
      "platform": "SPOTV NOW",
      "koreanCommentary": false
    },
    {
      "id": "coupang-2026-04-12-22:00-프리미어리그-선덜랜드-토트넘",
      "date": "2026-04-12",
      "time": "22:00",
      "sport": "축구",
      "league": "프리미어리그",
      "homeTeam": "선덜랜드",
      "awayTeam": "토트넘",
      "platform": "쿠팡플레이",
      "koreanCommentary": true
    },
    {
      "id": "coupang-2026-04-12-22:00-프리미어리그-크리스탈 팰리스-뉴캐슬",
      "date": "2026-04-12",
      "time": "22:00",
      "sport": "축구",
      "league": "프리미어리그",
      "homeTeam": "크리스탈 팰리스",
      "awayTeam": "뉴캐슬",
      "platform": "쿠팡플레이",
      "koreanCommentary": true
    },
    {
      "id": "coupang-2026-04-12-22:00-프리미어리그-노팅엄-아스톤 빌라",
      "date": "2026-04-12",
      "time": "22:00",
      "sport": "축구",
      "league": "프리미어리그",
      "homeTeam": "노팅엄",
      "awayTeam": "아스톤 빌라",
      "platform": "쿠팡플레이",
      "koreanCommentary": true
    },
    {
      "id": "coupang-2026-04-12-22:30-분데스리가-쾰른-베르더 브레멘",
      "date": "2026-04-12",
      "time": "22:30",
      "sport": "축구",
      "league": "분데스리가",
      "homeTeam": "쾰른",
      "awayTeam": "베르더 브레멘",
      "platform": "쿠팡플레이",
      "koreanCommentary": true
    },
    {
      "id": "coupang-2026-04-12-23:15-라리가-마요르카-라요 바예카노",
      "date": "2026-04-12",
      "time": "23:15",
      "sport": "축구",
      "league": "라리가",
      "homeTeam": "마요르카",
      "awayTeam": "라요 바예카노",
      "platform": "쿠팡플레이",
      "koreanCommentary": true
    },
    {
      "id": "coupang-2026-04-13-00:15-리그 1-툴루즈-릴",
      "date": "2026-04-13",
      "time": "00:15",
      "sport": "축구",
      "league": "리그 1",
      "homeTeam": "툴루즈",
      "awayTeam": "릴",
      "platform": "쿠팡플레이",
      "koreanCommentary": true
    },
    {
      "id": "coupang-2026-04-13-00:15-리그 1-니스-르 아브르",
      "date": "2026-04-13",
      "time": "00:15",
      "sport": "축구",
      "league": "리그 1",
      "homeTeam": "니스",
      "awayTeam": "르 아브르",
      "platform": "쿠팡플레이",
      "koreanCommentary": true
    },
    {
      "id": "coupang-2026-04-13-00:30-프리미어리그-첼시-맨시티",
      "date": "2026-04-13",
      "time": "00:30",
      "sport": "축구",
      "league": "프리미어리그",
      "homeTeam": "첼시",
      "awayTeam": "맨시티",
      "platform": "쿠팡플레이",
      "koreanCommentary": true
    },
    {
      "id": "coupang-2026-04-13-00:30-분데스리가-슈투트가르트-함부르크",
      "date": "2026-04-13",
      "time": "00:30",
      "sport": "축구",
      "league": "분데스리가",
      "homeTeam": "슈투트가르트",
      "awayTeam": "함부르크",
      "platform": "쿠팡플레이",
      "koreanCommentary": true
    },
    {
      "id": "spotvnow-2026-04-13-38042",
      "date": "2026-04-13",
      "time": "01:00",
      "sport": "축구",
      "league": "세리에A",
      "homeTeam": "볼로냐",
      "awayTeam": "레체",
      "platform": "SPOTV NOW",
      "koreanCommentary": false
    },
    {
      "id": "coupang-2026-04-13-01:30-라리가-셀타 비고-레알 오비에도",
      "date": "2026-04-13",
      "time": "01:30",
      "sport": "축구",
      "league": "라리가",
      "homeTeam": "셀타 비고",
      "awayTeam": "레알 오비에도",
      "platform": "쿠팡플레이",
      "koreanCommentary": true
    },
    {
      "id": "coupang-2026-04-13-01:30-라리가 2-카디스-안도라",
      "date": "2026-04-13",
      "time": "01:30",
      "sport": "축구",
      "league": "라리가 2",
      "homeTeam": "카디스",
      "awayTeam": "안도라",
      "platform": "쿠팡플레이",
      "koreanCommentary": true
    },
    {
      "id": "coupang-2026-04-13-02:30-분데스리가-마인츠-프라이부르크",
      "date": "2026-04-13",
      "time": "02:30",
      "sport": "축구",
      "league": "분데스리가",
      "homeTeam": "마인츠",
      "awayTeam": "프라이부르크",
      "platform": "쿠팡플레이",
      "koreanCommentary": true
    },
    {
      "id": "spotvnow-2026-04-13-38081",
      "date": "2026-04-13",
      "time": "02:35",
      "sport": "야구",
      "league": "MLB",
      "homeTeam": "샌프란시스코 자이언츠",
      "awayTeam": "볼티모어 오리올스",
      "platform": "SPOTV NOW",
      "koreanCommentary": true
    },
    {
      "id": "spotvnow-2026-04-13-38082",
      "date": "2026-04-13",
      "time": "02:40",
      "sport": "야구",
      "league": "MLB",
      "homeTeam": "뉴욕 양키스",
      "awayTeam": "탬파베이 레이스",
      "platform": "SPOTV NOW",
      "koreanCommentary": false
    },
    {
      "id": "spotvnow-2026-04-13-38043",
      "date": "2026-04-13",
      "time": "03:45",
      "sport": "축구",
      "league": "세리에A",
      "homeTeam": "코모 1907",
      "awayTeam": "인터 밀란",
      "platform": "SPOTV NOW",
      "koreanCommentary": true
    },
    {
      "id": "coupang-2026-04-13-03:45-리그 1-리옹-로리앙",
      "date": "2026-04-13",
      "time": "03:45",
      "sport": "축구",
      "league": "리그 1",
      "homeTeam": "리옹",
      "awayTeam": "로리앙",
      "platform": "쿠팡플레이",
      "koreanCommentary": true
    },
    {
      "id": "coupang-2026-04-13-04:00-라리가-아틀레틱-비야레알",
      "date": "2026-04-13",
      "time": "04:00",
      "sport": "축구",
      "league": "라리가",
      "homeTeam": "아틀레틱",
      "awayTeam": "비야레알",
      "platform": "쿠팡플레이",
      "koreanCommentary": true
    },
    {
      "id": "spotvnow-2026-04-13-38085",
      "date": "2026-04-13",
      "time": "05:10",
      "sport": "야구",
      "league": "MLB",
      "homeTeam": "텍사스 레인저스",
      "awayTeam": "LA 다저스",
      "platform": "SPOTV NOW",
      "koreanCommentary": true
    },
    {
      "id": "spotvnow-2026-04-13-38084",
      "date": "2026-04-13",
      "time": "05:10",
      "sport": "야구",
      "league": "MLB",
      "homeTeam": "휴스턴 애스트로스",
      "awayTeam": "시애틀 매리너스",
      "platform": "SPOTV NOW",
      "koreanCommentary": false
    },
    {
      "id": "spotvnow-2026-04-13-38083",
      "date": "2026-04-13",
      "time": "05:10",
      "sport": "야구",
      "league": "MLB",
      "homeTeam": "콜로라도 로키스",
      "awayTeam": "샌디에이고 파드리스",
      "platform": "SPOTV NOW",
      "koreanCommentary": false
    },
    {
      "id": "coupang-2026-04-13-07:00-NBA-올랜도-보스턴",
      "date": "2026-04-13",
      "time": "07:00",
      "sport": "농구",
      "league": "NBA",
      "homeTeam": "올랜도",
      "awayTeam": "보스턴",
      "platform": "쿠팡플레이",
      "koreanCommentary": true
    },
    {
      "id": "coupang-2026-04-13-07:00-NBA-샬럿-뉴욕",
      "date": "2026-04-13",
      "time": "07:00",
      "sport": "농구",
      "league": "NBA",
      "homeTeam": "샬럿",
      "awayTeam": "뉴욕",
      "platform": "쿠팡플레이",
      "koreanCommentary": true
    },
    {
      "id": "coupang-2026-04-13-07:00-NBA-애틀랜타-마이애미",
      "date": "2026-04-13",
      "time": "07:00",
      "sport": "농구",
      "league": "NBA",
      "homeTeam": "애틀랜타",
      "awayTeam": "마이애미",
      "platform": "쿠팡플레이",
      "koreanCommentary": true
    },
    {
      "id": "apple-tv-2026-04-13-08:00-MLS-ORL-CLB",
      "date": "2026-04-13",
      "time": "08:00",
      "sport": "축구",
      "league": "MLS",
      "homeTeam": "콜럼버스 크루",
      "awayTeam": "올랜도 시티 SC",
      "platform": "Apple TV+",
      "koreanCommentary": false
    },
    {
      "id": "spotvnow-2026-04-13-38086",
      "date": "2026-04-13",
      "time": "08:20",
      "sport": "야구",
      "league": "MLB",
      "homeTeam": "클리블랜드 가디언스",
      "awayTeam": "애틀랜타 브레이브스",
      "platform": "SPOTV NOW",
      "koreanCommentary": true
    },
    {
      "id": "coupang-2026-04-13-09:30-NBA-유타-LA 레이커스",
      "date": "2026-04-13",
      "time": "09:30",
      "sport": "농구",
      "league": "NBA",
      "homeTeam": "유타",
      "awayTeam": "LA 레이커스",
      "platform": "쿠팡플레이",
      "koreanCommentary": true
    },
    {
      "id": "coupang-2026-04-13-09:30-NBA-골든스테이트-LA 클리퍼스",
      "date": "2026-04-13",
      "time": "09:30",
      "sport": "농구",
      "league": "NBA",
      "homeTeam": "골든스테이트",
      "awayTeam": "LA 클리퍼스",
      "platform": "쿠팡플레이",
      "koreanCommentary": true
    },
    {
      "id": "coupang-2026-04-13-09:30-NBA-덴버-샌안토니오",
      "date": "2026-04-13",
      "time": "09:30",
      "sport": "농구",
      "league": "NBA",
      "homeTeam": "덴버",
      "awayTeam": "샌안토니오",
      "platform": "쿠팡플레이",
      "koreanCommentary": true
    },
    {
      "id": "tving-2026-04-13-18:30-KBO-KT-NC",
      "date": "2026-04-13",
      "time": "18:30",
      "sport": "야구",
      "league": "KBO",
      "homeTeam": "NC",
      "awayTeam": "KT",
      "platform": "티빙",
      "koreanCommentary": true
    },
    {
      "id": "tving-2026-04-13-18:30-KBO-롯데-LG",
      "date": "2026-04-13",
      "time": "18:30",
      "sport": "야구",
      "league": "KBO",
      "homeTeam": "LG",
      "awayTeam": "롯데",
      "platform": "티빙",
      "koreanCommentary": true
    },
    {
      "id": "tving-2026-04-13-18:30-KBO-두산-SSG",
      "date": "2026-04-13",
      "time": "18:30",
      "sport": "야구",
      "league": "KBO",
      "homeTeam": "SSG",
      "awayTeam": "두산",
      "platform": "티빙",
      "koreanCommentary": true
    },
    {
      "id": "tving-2026-04-13-18:30-KBO-삼성-한화",
      "date": "2026-04-13",
      "time": "18:30",
      "sport": "야구",
      "league": "KBO",
      "homeTeam": "한화",
      "awayTeam": "삼성",
      "platform": "티빙",
      "koreanCommentary": true
    },
    {
      "id": "tving-2026-04-13-18:30-KBO-키움-KIA",
      "date": "2026-04-13",
      "time": "18:30",
      "sport": "야구",
      "league": "KBO",
      "homeTeam": "KIA",
      "awayTeam": "키움",
      "platform": "티빙",
      "koreanCommentary": true
    },
    {
      "id": "spotvnow-2026-04-13-38198",
      "date": "2026-04-13",
      "time": "19:00",
      "sport": "농구",
      "league": "프로농구",
      "homeTeam": "삼성생명 블루밍스",
      "awayTeam": "하나은행",
      "platform": "SPOTV NOW",
      "koreanCommentary": true
    },
    {
      "id": "coupang-2026-04-14-03:00-ACLE-알 힐랄-알 사드",
      "date": "2026-04-14",
      "time": "03:00",
      "sport": "축구",
      "league": "AFC 챔피언스리그 엘리트",
      "homeTeam": "알 힐랄",
      "awayTeam": "알 사드",
      "platform": "쿠팡플레이",
      "koreanCommentary": true
    },
    {
      "id": "spotvnow-2026-04-14-38044",
      "date": "2026-04-14",
      "time": "03:45",
      "sport": "축구",
      "league": "세리에A",
      "homeTeam": "피오렌티나",
      "awayTeam": "라치오",
      "platform": "SPOTV NOW",
      "koreanCommentary": false
    },
    {
      "id": "coupang-2026-04-14-04:00-프리미어리그-맨유-리즈",
      "date": "2026-04-14",
      "time": "04:00",
      "sport": "축구",
      "league": "프리미어리그",
      "homeTeam": "맨유",
      "awayTeam": "리즈",
      "platform": "쿠팡플레이",
      "koreanCommentary": true
    },
    {
      "id": "coupang-2026-04-14-04:00-라리가-레반테-헤타페",
      "date": "2026-04-14",
      "time": "04:00",
      "sport": "축구",
      "league": "라리가",
      "homeTeam": "레반테",
      "awayTeam": "헤타페",
      "platform": "쿠팡플레이",
      "koreanCommentary": true
    },
    {
      "id": "spotvnow-2026-04-14-38154",
      "date": "2026-04-14",
      "time": "07:40",
      "sport": "야구",
      "league": "MLB",
      "homeTeam": "워싱턴 내셔널스",
      "awayTeam": "피츠버그 파이리츠",
      "platform": "SPOTV NOW",
      "koreanCommentary": true
    },
    {
      "id": "spotvnow-2026-04-14-38153",
      "date": "2026-04-14",
      "time": "07:40",
      "sport": "야구",
      "league": "MLB",
      "homeTeam": "시카고 컵스",
      "awayTeam": "필라델피아 필리스",
      "platform": "SPOTV NOW",
      "koreanCommentary": false
    },
    {
      "id": "spotvnow-2026-04-14-38155",
      "date": "2026-04-14",
      "time": "08:05",
      "sport": "야구",
      "league": "MLB",
      "homeTeam": "LA 에인절스",
      "awayTeam": "뉴욕 양키스",
      "platform": "SPOTV NOW",
      "koreanCommentary": true
    },
    {
      "id": "spotvnow-2026-04-14-38156",
      "date": "2026-04-14",
      "time": "10:40",
      "sport": "야구",
      "league": "MLB",
      "homeTeam": "텍사스 레인저스",
      "awayTeam": "애슬레틱스",
      "platform": "SPOTV NOW",
      "koreanCommentary": false
    },
    {
      "id": "spotvnow-2026-04-14-38157",
      "date": "2026-04-14",
      "time": "11:10",
      "sport": "야구",
      "league": "MLB",
      "homeTeam": "뉴욕 메츠",
      "awayTeam": "LA 다저스",
      "platform": "SPOTV NOW",
      "koreanCommentary": true
    },
    {
      "id": "tving-2026-04-14-18:30-KBO-KT-NC",
      "date": "2026-04-14",
      "time": "18:30",
      "sport": "야구",
      "league": "KBO",
      "homeTeam": "NC",
      "awayTeam": "KT",
      "platform": "티빙",
      "koreanCommentary": true
    },
    {
      "id": "tving-2026-04-14-18:30-KBO-롯데-LG",
      "date": "2026-04-14",
      "time": "18:30",
      "sport": "야구",
      "league": "KBO",
      "homeTeam": "LG",
      "awayTeam": "롯데",
      "platform": "티빙",
      "koreanCommentary": true
    },
    {
      "id": "tving-2026-04-14-18:30-KBO-두산-SSG",
      "date": "2026-04-14",
      "time": "18:30",
      "sport": "야구",
      "league": "KBO",
      "homeTeam": "SSG",
      "awayTeam": "두산",
      "platform": "티빙",
      "koreanCommentary": true
    },
    {
      "id": "tving-2026-04-14-18:30-KBO-삼성-한화",
      "date": "2026-04-14",
      "time": "18:30",
      "sport": "야구",
      "league": "KBO",
      "homeTeam": "한화",
      "awayTeam": "삼성",
      "platform": "티빙",
      "koreanCommentary": true
    },
    {
      "id": "tving-2026-04-14-18:30-KBO-키움-KIA",
      "date": "2026-04-14",
      "time": "18:30",
      "sport": "야구",
      "league": "KBO",
      "homeTeam": "KIA",
      "awayTeam": "키움",
      "platform": "티빙",
      "koreanCommentary": true
    },
    {
      "id": "spotvnow-2026-04-14-38205",
      "date": "2026-04-14",
      "time": "19:00",
      "sport": "농구",
      "league": "프로농구",
      "homeTeam": "우리은행 우리WON",
      "awayTeam": "KB스타즈",
      "platform": "SPOTV NOW",
      "koreanCommentary": true
    }
  ]
}